{
  "id": "gc-008",
  "type": "memory-game",
  "version": 1,
  "difficulty": 2,
  "tags": ["garbage-collection", "array"],
  "payload": {
    "codeSnippet": "let arr = [{x:1}, {x:2}];\nlet last = arr.pop();",
    "highlightedLine": 2,
    "objects": [
      { "id": "arr-var", "label": "Variable arr", "x": 50, "y": 200 },
      { "id": "arr-obj", "label": "Array [obj1, obj2]", "x": 350, "y": 200 },
      { "id": "obj1", "label": "Object {x:1}", "x": 50, "y": 350 },
      { "id": "obj2", "label": "Object {x:2}", "x": 350, "y": 350 },
      { "id": "last-var", "label": "Variable last", "x": 550, "y": 100 }
    ],
    "links": [
      { "from": "arr-var", "to": "arr-obj", "label": "ref" },
      { "from": "arr-obj", "to": "obj1", "label": "0" },
      { "from": "arr-obj", "to": "obj2", "label": "1" },
      { "from": "last-var", "to": "obj2", "label": "ref" }
    ],
    "rootIds": ["global"],
    "rootLinks": [
      { "from": "global", "to": "arr-var" },
      { "from": "global", "to": "last-var" }
    ]
  },
  "correctAnswer": []
}
